<?xml version="1.0" encoding="utf-8"?>

<Deployment xmlns="http://schemas.microsoft.com/windowsphone/2009/deployment" AppPlatformVersion="7.0">
  <App xmlns="" ProductID="{0bde1cc2-b386-4150-b3b8-354077cd3261}" Title="WindowsPhoneTestRunner" RuntimeType="Silverlight" Version="1.0.0.0" Genre="apps.normal"  Author="WindowsPhoneTestRunner author" Description="Sample description" Publisher="WindowsPhoneTestRunner">
    <IconPath IsRelative="true" IsResource="false">ApplicationIcon.png</IconPath>
    <Capabilities>
      <Capability Name="ID_CAP_GAMERSERVICES"/>
      <Capability Name="ID_CAP_IDENTITY_DEVICE"/>
      <Capability Name="ID_CAP_IDENTITY_USER"/>
      <Capability Name="ID_CAP_LOCATION"/>
      <Capability Name="ID_CAP_MEDIALIB"/>
      <Capability Name="ID_CAP_MICROPHONE"/>
      <Capability Name="ID_CAP_NETWORKING"/>
      <Capability Name="ID_CAP_PHONEDIALER"/>
      <Capability Name="ID_CAP_PUSH_NOTIFICATION"/>
      <Capability Name="ID_CAP_SENSORS"/>
      <Capability Name="ID_CAP_WEBBROWSERCOMPONENT"/>
    </Capabilities>
    <Tasks>
      <DefaultTask  Name ="_default" NavigationPage="MainPage.xaml"/>
    </Tasks>
    <Tokens>
      <PrimaryToken TokenID="WindowsPhoneTestRunnerToken" TaskName="_default">
        <TemplateType5>
          <BackgroundImageURI IsRelative="true" IsResource="false">Background.png</BackgroundImageURI>
          <Count>0</Count>
          <Title>WindowsPhoneTestRunner</Title>
        </TemplateType5>
      </PrimaryToken>
    </Tokens>
  </App>
</Deployment>
